esi_utils_textformat/__init__.py
esi_utils_textformat/text.py
esi_utils_textformat-1.0.1.dist-info/licenses/LICENSE.md
esi_utils_textformat-1.0.1.dist-info/METADATA
esi_utils_textformat-1.0.1.dist-info/WHEEL
esi_utils_textformat-1.0.1.dist-info/top_level.txt
esi_utils_textformat-1.0.1.dist-info/RECORD
